MANIFEST.in
README.md
setup.cfg
setup.py
aiohttp_GraphQL.egg-info/PKG-INFO
aiohttp_GraphQL.egg-info/SOURCES.txt
aiohttp_GraphQL.egg-info/dependency_links.txt
aiohttp_GraphQL.egg-info/requires.txt
aiohttp_GraphQL.egg-info/top_level.txt
aiohttp_graphql/__init__.py
aiohttp_graphql/graphqlview.py
aiohttp_graphql/render_graphiql.py
aiohttp_graphql.egg-info/PKG-INFO
aiohttp_graphql.egg-info/SOURCES.txt
aiohttp_graphql.egg-info/dependency_links.txt
aiohttp_graphql.egg-info/requires.txt
aiohttp_graphql.egg-info/top_level.txt