Metadata-Version: 1.1
Name: aiohttp-graphql
Version: 1.0.0
Summary: Adds GraphQL support to your aiohttp application
Home-page: https://github.com/dfee/aiohttp-graphql
Author: Devin Fee
Author-email: devin@devinfee.com
License: MIT
Download-URL: https://github.com/dfee/aiohttp-graphql/releases
Keywords: api graphql protocol aiohttp
Platform: any
Classifier: Development Status :: 5 - Production/Stable
Classifier: Intended Audience :: Developers
Classifier: Topic :: Software Development :: Libraries
Classifier: Programming Language :: Python :: 3.5
Classifier: Programming Language :: Python :: 3.6
Classifier: License :: OSI Approved :: MIT License
